Metadata-Version: 1.1
Name: python-c
Version: 1.0
Summary: A lazy alternative to python -c
Home-page: https://github.com/jadnohra/python-c
Author: Jad Nohra
Author-email: jadnohra@gmail.com
License: MIT
Download-URL: https://github.com/jadnohra/python-c/archive/v1.0.tar.gz
Platform: UNKNOWN
